LICENSE
MANIFEST.in
README.md
pyproject.toml
setup.cfg
setup.py
tests.py
versioneer.py
fishersrc/__init__.py
fishersrc/_version.py
fishersrc/tableprinter.py
fishersrc.egg-info/PKG-INFO
fishersrc.egg-info/SOURCES.txt
fishersrc.egg-info/dependency_links.txt
fishersrc.egg-info/requires.txt
fishersrc.egg-info/top_level.txt
fishersrc.egg-info/zip-safe
src/cfisher.pyx